{"frames": [

{
	"filename": "cursor_box.png",
	"frame": {"x":1,"y":1715,"w":32,"h":32},
	"rotated": false,
	"trimmed": false,
	"spriteSourceSize": {"x":0,"y":0,"w":32,"h":32},
	"sourceSize": {"w":32,"h":32}
},
{
	"filename": "flesh_child_full_1.png",
	"frame": {"x":1,"y":131,"w":64,"h":64},
	"rotated": false,
	"trimmed": false,
	"spriteSourceSize": {"x":0,"y":0,"w":64,"h":64},
	"sourceSize": {"w":64,"h":64}
},
{
	"filename": "flesh_child_full_2.png",
	"frame": {"x":1,"y":857,"w":64,"h":64},
	"rotated": false,
	"trimmed": false,
	"spriteSourceSize": {"x":0,"y":0,"w":64,"h":64},
	"sourceSize": {"w":64,"h":64}
},
{
	"filename": "flesh_child_full_3.png",
	"frame": {"x":1,"y":1253,"w":64,"h":64},
	"rotated": false,
	"trimmed": false,
	"spriteSourceSize": {"x":0,"y":0,"w":64,"h":64},
	"sourceSize": {"w":64,"h":64}
},
{
	"filename": "flesh_child_full_4.png",
	"frame": {"x":1,"y":1319,"w":64,"h":64},
	"rotated": false,
	"trimmed": false,
	"spriteSourceSize": {"x":0,"y":0,"w":64,"h":64},
	"sourceSize": {"w":64,"h":64}
},
{
	"filename": "flesh_child_full_5.png",
	"frame": {"x":1,"y":1385,"w":64,"h":64},
	"rotated": false,
	"trimmed": false,
	"spriteSourceSize": {"x":0,"y":0,"w":64,"h":64},
	"sourceSize": {"w":64,"h":64}
},
{
	"filename": "flesh_child_full_6.png",
	"frame": {"x":1,"y":1451,"w":64,"h":64},
	"rotated": false,
	"trimmed": false,
	"spriteSourceSize": {"x":0,"y":0,"w":64,"h":64},
	"sourceSize": {"w":64,"h":64}
},
{
	"filename": "flesh_child_full_7.png",
	"frame": {"x":1,"y":1517,"w":64,"h":64},
	"rotated": false,
	"trimmed": false,
	"spriteSourceSize": {"x":0,"y":0,"w":64,"h":64},
	"sourceSize": {"w":64,"h":64}
},
{
	"filename": "flesh_child_full_8.png",
	"frame": {"x":1,"y":1583,"w":64,"h":64},
	"rotated": false,
	"trimmed": false,
	"spriteSourceSize": {"x":0,"y":0,"w":64,"h":64},
	"sourceSize": {"w":64,"h":64}
},
{
	"filename": "flesh_child_full_9.png",
	"frame": {"x":1,"y":1649,"w":64,"h":64},
	"rotated": false,
	"trimmed": false,
	"spriteSourceSize": {"x":0,"y":0,"w":64,"h":64},
	"sourceSize": {"w":64,"h":64}
},
{
	"filename": "flesh_child_full_10.png",
	"frame": {"x":1,"y":197,"w":64,"h":64},
	"rotated": false,
	"trimmed": false,
	"spriteSourceSize": {"x":0,"y":0,"w":64,"h":64},
	"sourceSize": {"w":64,"h":64}
},
{
	"filename": "flesh_child_full_11.png",
	"frame": {"x":1,"y":263,"w":64,"h":64},
	"rotated": false,
	"trimmed": false,
	"spriteSourceSize": {"x":0,"y":0,"w":64,"h":64},
	"sourceSize": {"w":64,"h":64}
},
{
	"filename": "flesh_child_full_12.png",
	"frame": {"x":1,"y":329,"w":64,"h":64},
	"rotated": false,
	"trimmed": false,
	"spriteSourceSize": {"x":0,"y":0,"w":64,"h":64},
	"sourceSize": {"w":64,"h":64}
},
{
	"filename": "flesh_child_full_13.png",
	"frame": {"x":1,"y":395,"w":64,"h":64},
	"rotated": false,
	"trimmed": false,
	"spriteSourceSize": {"x":0,"y":0,"w":64,"h":64},
	"sourceSize": {"w":64,"h":64}
},
{
	"filename": "flesh_child_full_14.png",
	"frame": {"x":1,"y":461,"w":64,"h":64},
	"rotated": false,
	"trimmed": false,
	"spriteSourceSize": {"x":0,"y":0,"w":64,"h":64},
	"sourceSize": {"w":64,"h":64}
},
{
	"filename": "flesh_child_full_15.png",
	"frame": {"x":1,"y":527,"w":64,"h":64},
	"rotated": false,
	"trimmed": false,
	"spriteSourceSize": {"x":0,"y":0,"w":64,"h":64},
	"sourceSize": {"w":64,"h":64}
},
{
	"filename": "flesh_child_full_16.png",
	"frame": {"x":1,"y":593,"w":64,"h":64},
	"rotated": false,
	"trimmed": false,
	"spriteSourceSize": {"x":0,"y":0,"w":64,"h":64},
	"sourceSize": {"w":64,"h":64}
},
{
	"filename": "flesh_child_full_17.png",
	"frame": {"x":1,"y":659,"w":64,"h":64},
	"rotated": false,
	"trimmed": false,
	"spriteSourceSize": {"x":0,"y":0,"w":64,"h":64},
	"sourceSize": {"w":64,"h":64}
},
{
	"filename": "flesh_child_full_18.png",
	"frame": {"x":1,"y":725,"w":64,"h":64},
	"rotated": false,
	"trimmed": false,
	"spriteSourceSize": {"x":0,"y":0,"w":64,"h":64},
	"sourceSize": {"w":64,"h":64}
},
{
	"filename": "flesh_child_full_19.png",
	"frame": {"x":1,"y":791,"w":64,"h":64},
	"rotated": false,
	"trimmed": false,
	"spriteSourceSize": {"x":0,"y":0,"w":64,"h":64},
	"sourceSize": {"w":64,"h":64}
},
{
	"filename": "flesh_child_full_20.png",
	"frame": {"x":1,"y":923,"w":64,"h":64},
	"rotated": false,
	"trimmed": false,
	"spriteSourceSize": {"x":0,"y":0,"w":64,"h":64},
	"sourceSize": {"w":64,"h":64}
},
{
	"filename": "flesh_child_full_21.png",
	"frame": {"x":1,"y":989,"w":64,"h":64},
	"rotated": false,
	"trimmed": false,
	"spriteSourceSize": {"x":0,"y":0,"w":64,"h":64},
	"sourceSize": {"w":64,"h":64}
},
{
	"filename": "flesh_child_full_22.png",
	"frame": {"x":1,"y":1055,"w":64,"h":64},
	"rotated": false,
	"trimmed": false,
	"spriteSourceSize": {"x":0,"y":0,"w":64,"h":64},
	"sourceSize": {"w":64,"h":64}
},
{
	"filename": "flesh_child_full_23.png",
	"frame": {"x":1,"y":1121,"w":64,"h":64},
	"rotated": false,
	"trimmed": false,
	"spriteSourceSize": {"x":0,"y":0,"w":64,"h":64},
	"sourceSize": {"w":64,"h":64}
},
{
	"filename": "flesh_child_full_24.png",
	"frame": {"x":1,"y":1187,"w":64,"h":64},
	"rotated": false,
	"trimmed": false,
	"spriteSourceSize": {"x":0,"y":0,"w":64,"h":64},
	"sourceSize": {"w":64,"h":64}
},
{
	"filename": "npc.png",
	"frame": {"x":1,"y":1,"w":64,"h":128},
	"rotated": false,
	"trimmed": false,
	"spriteSourceSize": {"x":0,"y":0,"w":64,"h":128},
	"sourceSize": {"w":64,"h":128}
},
{
	"filename": "signpost.png",
	"frame": {"x":1,"y":1749,"w":32,"h":32},
	"rotated": false,
	"trimmed": false,
	"spriteSourceSize": {"x":0,"y":0,"w":32,"h":32},
	"sourceSize": {"w":32,"h":32}
},
{
	"filename": "textbox_0_top_left_corner.png",
	"frame": {"x":35,"y":1715,"w":10,"h":10},
	"rotated": false,
	"trimmed": false,
	"spriteSourceSize": {"x":0,"y":0,"w":10,"h":10},
	"sourceSize": {"w":10,"h":10}
},
{
	"filename": "textbox_1_top_right_corner.png",
	"frame": {"x":47,"y":1715,"w":10,"h":10},
	"rotated": false,
	"trimmed": false,
	"spriteSourceSize": {"x":0,"y":0,"w":10,"h":10},
	"sourceSize": {"w":10,"h":10}
},
{
	"filename": "textbox_2_bot_left_corner.png",
	"frame": {"x":35,"y":1727,"w":10,"h":10},
	"rotated": false,
	"trimmed": false,
	"spriteSourceSize": {"x":0,"y":0,"w":10,"h":10},
	"sourceSize": {"w":10,"h":10}
},
{
	"filename": "textbox_3_bot_right_corner.png",
	"frame": {"x":47,"y":1727,"w":10,"h":10},
	"rotated": false,
	"trimmed": false,
	"spriteSourceSize": {"x":0,"y":0,"w":10,"h":10},
	"sourceSize": {"w":10,"h":10}
},
{
	"filename": "textbox_4_top_side.png",
	"frame": {"x":35,"y":1739,"w":10,"h":10},
	"rotated": false,
	"trimmed": false,
	"spriteSourceSize": {"x":0,"y":0,"w":10,"h":10},
	"sourceSize": {"w":10,"h":10}
},
{
	"filename": "textbox_5_left_side.png",
	"frame": {"x":47,"y":1739,"w":10,"h":10},
	"rotated": false,
	"trimmed": false,
	"spriteSourceSize": {"x":0,"y":0,"w":10,"h":10},
	"sourceSize": {"w":10,"h":10}
},
{
	"filename": "textbox_6_right_side.png",
	"frame": {"x":35,"y":1751,"w":10,"h":10},
	"rotated": false,
	"trimmed": false,
	"spriteSourceSize": {"x":0,"y":0,"w":10,"h":10},
	"sourceSize": {"w":10,"h":10}
},
{
	"filename": "textbox_7_bot_side.png",
	"frame": {"x":47,"y":1751,"w":10,"h":10},
	"rotated": false,
	"trimmed": false,
	"spriteSourceSize": {"x":0,"y":0,"w":10,"h":10},
	"sourceSize": {"w":10,"h":10}
},
{
	"filename": "textbox_8_center.png",
	"frame": {"x":35,"y":1763,"w":10,"h":10},
	"rotated": false,
	"trimmed": false,
	"spriteSourceSize": {"x":0,"y":0,"w":10,"h":10},
	"sourceSize": {"w":10,"h":10}
},
{
	"filename": "textbox_9_speech_arrow.png",
	"frame": {"x":47,"y":1763,"w":10,"h":10},
	"rotated": false,
	"trimmed": false,
	"spriteSourceSize": {"x":0,"y":0,"w":10,"h":10},
	"sourceSize": {"w":10,"h":10}
}],
"meta": {
	"app": "https://www.codeandweb.com/texturepacker",
	"version": "1.0",
	"image": "spritesheet.png",
	"format": "RGBA8888",
	"size": {"w":66,"h":1782},
	"scale": "1",
	"smartupdate": "$TexturePacker:SmartUpdate:8789c13692db52a63144bde1724e8f6c:d6f4e478ce707078ead26d3580902570:729adc6043343cfda41c447ce8f464d6$"
}
}
